{"id": "26591553_ru", "text": "Цель исследования.\nОценка роли хронической обструктивной болезни легких (ХОБЛ) в развитии неблагоприятных исходов отдаленного (годового) прогноза инфаркта миокарда с подъемом сегмента ST (ИМпST).\nМатериалы и методы.\nОбследовали 529 пациентов с диагнозом ИМпST без возрастных ограничений.\nВ 1-ю группу вошли 65 (12,3%) пациентов с диагностированной ранее ХОБЛ, во 2-ю - 464 (87,7%) пациента без ХОБЛ.\nГодовой прогноз изучен у 384 (81,5%) пациентов.\nОценены следующие исходы: развитие повторного ИМ, прогрессирование стенокардии, декомпенсация хронической сердечной недостаточности (ХСН), повторные чрескожные вмешательства на коронарных артериях, острое нарушение мозгового кровообращения, смерть.\nРезультаты.\nРаспространенность ХОБЛ среди пациентов с ИМпST составила 12,3%.\nНеблагоприятный годовой прогноз статистически значимо чаще регистрировался в группе с сочетанной патологией независимо от возраста, пола и факта курения.\nНаличие ХОБЛ увеличивало риск развития комбинированных оцениваемых исходов в течение года после ИМ в 1,9 раза, а риск декомпенсации ХСН в течение года после ИМпST в 2,6 раза.\nЗаключение.\nХОБЛ может являться самостоятельным фактором риска развития неблагоприятных исходов в течение года после ИМ.\n", "entity_types": ["ANATOMY", "DISO", "ANATOMY", "ANATOMY", "ANATOMY", "DISO", "DISO", "DISO", "DISO", "DISO", "DISO", "DISO", "DISO", "DISO", "DISO", "DISO", "DISO", "DISO", "DISO", "DISO", "DISO", "DISO", "DISO", "DISO", "DISO", "DISO", "DISO", "DISO", "DISO", "DISO", "DISO", "DISO", "DISO", "ANATOMY", "ANATOMY", "DISO", "DISO", "ANATOMY"], "entity_start_chars": [636, 494, 65, 554, 625, 394, 728, 1115, 542, 1024, 581, 554, 528, 1046, 515, 146, 646, 1220, 146, 43, 1060, 1046, 860, 528, 31, 564, 751, 146, 73, 254, 646, 354, 1085, 625, 155, 936, 188, 663], "entity_end_chars": [644, 496, 71, 563, 635, 398, 732, 1119, 579, 1026, 584, 579, 579, 1063, 526, 163, 687, 1222, 154, 71, 1063, 1059, 881, 541, 71, 579, 756, 186, 77, 259, 662, 358, 1090, 644, 163, 940, 193, 672], "word_start_chars": [0, 5, 19, 26, 31, 43, 57, 65, 72, 79, 81, 90, 106, 114, 126, 137, 146, 155, 164, 166, 175, 184, 187, 196, 206, 208, 216, 228, 232, 242, 244, 254, 260, 264, 275, 288, 290, 294, 301, 307, 310, 318, 328, 330, 348, 354, 360, 363, 367, 369, 373, 381, 390, 394, 400, 408, 416, 423, 425, 429, 437, 448, 456, 466, 474, 483, 494, 498, 515, 528, 542, 554, 564, 580, 587, 597, 608, 622, 625, 636, 646, 653, 663, 673, 689, 697, 709, 728, 733, 739, 749, 751, 757, 767, 774, 790, 798, 806, 820, 828, 833, 849, 851, 858, 860, 871, 882, 893, 896, 906, 911, 913, 919, 928, 936, 941, 953, 958, 967, 983, 995, 1003, 1005, 1013, 1018, 1024, 1027, 1029, 1033, 1039, 1041, 1046, 1060, 1064, 1066, 1074, 1079, 1085, 1091, 1093, 1097, 1103, 1115, 1120, 1126, 1135, 1151, 1160, 1166, 1175, 1191, 1199, 1201, 1209, 1214, 1220], "word_end_chars": [4, 18, 25, 30, 42, 56, 64, 71, 78, 80, 89, 105, 113, 125, 136, 145, 154, 163, 165, 174, 183, 186, 195, 205, 207, 215, 227, 231, 241, 243, 253, 259, 263, 274, 287, 289, 293, 300, 306, 309, 317, 327, 329, 347, 353, 359, 362, 366, 368, 372, 380, 389, 393, 399, 407, 415, 422, 424, 428, 436, 447, 455, 465, 473, 482, 493, 497, 514, 527, 541, 553, 563, 579, 586, 596, 607, 621, 624, 635, 645, 652, 662, 672, 688, 696, 708, 727, 732, 738, 748, 750, 756, 766, 773, 789, 797, 805, 819, 827, 832, 848, 850, 857, 859, 870, 881, 892, 895, 905, 910, 912, 918, 927, 935, 940, 952, 957, 966, 982, 994, 1002, 1004, 1012, 1017, 1023, 1026, 1028, 1032, 1038, 1040, 1045, 1059, 1063, 1065, 1073, 1078, 1084, 1090, 1092, 1096, 1102, 1114, 1119, 1125, 1134, 1150, 1159, 1165, 1174, 1190, 1198, 1200, 1208, 1213, 1219, 1223]}