{"id": "26977624_ru", "text": "Цель исследования - изучение эффективности включения ремаксола в схему комплексного лечения больных с алкогольным абстинентным синдромом.\nМатериал и методы.\nЛечили 80 пациентов с алкогольной зависимостью и клиническими признаками алкогольного абстинентного синдрома в стационарных условиях.  Все пациенты получали базисную терапию в соответствии с применяемыми стандартами лечения; 40 больным (основная группа) был назначен ремаксол внутривенно капельно 2 раза в день (утром и днем) по 400 мл в течение 7 дней, в контрольной группе (40 человек) использовался физиологический раствор с 25% сульфатом магния (10 мл) и 4% хлоридом калия (10 мл).\nРезультаты.  Эффективность включения ремаксола в комплексную терапию состояла в более быстром купировании астенического синдрома, редукции таких явлений, как напряженность, дисфория, головная боль и нарушение координаторных проб.\nУ пациентов, получавших ремаксол, выявлена тенденция к более быстрой редукции аффективного (р=0,08) и поведенческого (р=0,09) компонентов синдрома патологического влечения к алкоголю.\nГепатопротективные и детоксикационные свойства препарата нашли подтверждение в достоверно значимом снижении показателей АЛТ и АСТ к 20-му дню лечения, кроме того выявлены достоверная положительная динамика показателей липидного обмена к 7-му дню лечения и нормализующее действие на процессы тканевого дыхания.\nНежелательных явлений, связанных с исследуемым препаратом, отмечено не было.\nЗаключение.\nПолученные данные позволяют рекомендовать включение ремаксола в комплексную терапию алкогольного абстинентного синдрома с целью повышения эффективности лечения.\n", "entity_types": ["CHEM", "DISO", "DISO", "CHEM", "CHEM", "CHEM", "CHEM", "DISO", "ANATOMY", "CHEM", "CHEM", "DISO", "CHEM", "DISO", "CHEM", "DISO", "DISO", "DISO", "CHEM", "DISO", "DISO", "CHEM", "CHEM", "DISO", "CHEM", "CHEM", "CHEM", "CHEM", "DISO", "DISO", "CHEM", "DISO", "DISO", "ANATOMY"], "entity_start_chars": [628, 826, 801, 559, 589, 585, 619, 816, 826, 1275, 1508, 243, 53, 749, 1183, 230, 1011, 1020, 424, 102, 1540, 619, 1177, 179, 599, 897, 616, 680, 842, 1553, 575, 114, 835, 1348], "entity_end_chars": [633, 839, 814, 582, 605, 605, 633, 824, 834, 1284, 1517, 265, 62, 771, 1186, 265, 1055, 1055, 432, 136, 1575, 627, 1180, 203, 605, 905, 633, 689, 871, 1575, 582, 136, 839, 1357], "word_start_chars": [0, 5, 18, 20, 29, 43, 53, 63, 65, 71, 84, 92, 100, 102, 114, 127, 138, 147, 149, 157, 164, 167, 177, 179, 191, 204, 206, 219, 230, 243, 257, 266, 268, 281, 292, 296, 305, 314, 323, 331, 333, 346, 348, 361, 373, 382, 385, 393, 403, 411, 415, 424, 433, 445, 454, 456, 461, 463, 468, 475, 477, 483, 486, 490, 493, 495, 503, 505, 511, 513, 525, 532, 536, 545, 559, 575, 583, 585, 589, 599, 606, 610, 614, 616, 619, 628, 634, 638, 643, 656, 670, 680, 690, 692, 704, 712, 721, 723, 729, 737, 749, 763, 773, 782, 788, 797, 801, 816, 826, 835, 840, 842, 852, 867, 873, 875, 886, 897, 907, 916, 926, 928, 934, 942, 951, 964, 973, 975, 990, 999, 1011, 1020, 1036, 1045, 1047, 1057, 1076, 1078, 1095, 1104, 1114, 1120, 1134, 1136, 1147, 1156, 1165, 1177, 1181, 1183, 1187, 1189, 1195, 1199, 1208, 1214, 1219, 1228, 1240, 1254, 1263, 1275, 1285, 1292, 1294, 1299, 1303, 1311, 1313, 1327, 1336, 1339, 1348, 1358, 1367, 1381, 1390, 1400, 1402, 1414, 1426, 1435, 1438, 1444, 1456, 1467, 1474, 1484, 1498, 1508, 1518, 1520, 1532, 1540, 1553, 1567, 1576, 1578, 1584, 1594, 1608], "word_end_chars": [4, 17, 19, 28, 42, 52, 62, 64, 70, 83, 91, 99, 101, 113, 126, 137, 146, 148, 156, 163, 166, 176, 178, 190, 203, 205, 218, 229, 242, 256, 265, 267, 280, 290, 295, 304, 313, 322, 330, 332, 345, 347, 360, 372, 381, 384, 392, 402, 410, 414, 423, 432, 444, 453, 455, 460, 462, 467, 474, 476, 482, 485, 489, 492, 494, 502, 504, 510, 512, 524, 531, 535, 544, 558, 574, 582, 584, 588, 598, 605, 609, 613, 615, 618, 627, 633, 637, 642, 654, 669, 679, 689, 691, 703, 711, 720, 722, 728, 736, 748, 762, 772, 781, 787, 796, 800, 815, 825, 834, 839, 841, 851, 866, 872, 874, 885, 896, 906, 915, 925, 927, 933, 941, 950, 963, 972, 974, 989, 998, 1010, 1019, 1035, 1044, 1046, 1056, 1075, 1077, 1094, 1103, 1113, 1119, 1133, 1135, 1146, 1155, 1164, 1176, 1180, 1182, 1186, 1188, 1194, 1198, 1207, 1213, 1218, 1227, 1239, 1253, 1262, 1274, 1284, 1291, 1293, 1298, 1302, 1310, 1312, 1326, 1335, 1338, 1347, 1357, 1366, 1380, 1389, 1399, 1401, 1413, 1425, 1434, 1437, 1443, 1455, 1466, 1473, 1483, 1497, 1507, 1517, 1519, 1531, 1539, 1552, 1566, 1575, 1577, 1583, 1593, 1607, 1616]}