{"id": "26978493_ru", "text": "Цель исследования - оценка эффективности и безопасности терапии D-, L-гопантеновой кислотой (пантогам актив) когнитивных и тревожных нарушений у пациентов с артериальной гипертензией.\nМатериал и методы.\nНаблюдали 80 пациентов кардиологического стационара с верифицированным диагнозом артериальной гипертензии и коморбидными когнитивными и тревожными нарушениями; 50 пациентов составили основную группу, 30 пациентов - группу контроля.\nВсе пациенты получали стандартную кардиотропную гипотензивную терапию.  В комплексную терапию пациентов основной группы был включен пантогам актив в суточной дозе от 600 до 1200 мг.\nПроводилось психопатологическое и психометрическое обследование с сопоставлением полученных данных с динамикой соматических показателей (ЭКГ, суточное мониторирование артериального давления, биохимический анализ крови).\nДлительность терапии D-, L-гопантеновой кислотой составила 28 дней.\nРезультаты.\nПолучены данные о достоверной редукции как когнитивных, так и тревожных нарушений в основной группе по сравнению с контрольной, а также у пациентов, перенесших острое нарушение мозгового кровообращения в анамнезе.\nПоложительная динамика наблюдалась на протяжении всего времени лечения.\nЗаключение.\nПодтверждена возможность использования D-, L-гопантеновой кислоты (пантогам актив) в качестве препарата выбора с бимодальной ноотропной и транквилизирующей активностью для лечения когнитивных и тревожных нарушений у пациентов с артериальной гипертензией.\nПоказано, что в процессе терапии пантогамом актив происходит быстрая (в течение первой недели терапии) и достоверная редукция тревожных и когнитивных нарушений.\n", "entity_types": ["DISO", "DISO", "DISO", "DISO", "DISO", "DISO", "DISO", "CHEM", "DISO", "DISO", "DISO", "ANATOMY", "CHEM", "DISO", "DISO", "CHEM", "CHEM", "CHEM", "CHEM", "CHEM", "CHEM", "CHEM", "CHEM", "CHEM", "DISO", "ANATOMY", "ANATOMY", "CHEM", "CHEM", "DISO", "ANATOMY", "DISO", "DISO", "DISO", "DISO", "DISO", "DISO", "ANATOMY", "ANATOMY", "DISO", "CHEM", "DISO", "CHEM", "DISO", "DISO", "CHEM", "CHEM"], "entity_start_chars": [284, 1395, 1419, 324, 350, 157, 1608, 858, 960, 989, 170, 1443, 83, 123, 1077, 864, 93, 1254, 70, 64, 567, 1260, 1282, 1503, 311, 157, 829, 1273, 877, 1409, 284, 979, 339, 1596, 1620, 109, 133, 784, 1094, 1084, 567, 297, 1282, 1443, 1456, 1503, 93], "entity_end_chars": [308, 1406, 1428, 336, 361, 182, 1629, 885, 971, 998, 182, 1455, 91, 142, 1118, 885, 107, 1280, 91, 91, 581, 1280, 1296, 1519, 361, 169, 834, 1280, 885, 1428, 296, 998, 361, 1605, 1629, 120, 142, 797, 1103, 1118, 575, 308, 1290, 1468, 1468, 1513, 101], "word_start_chars": [0, 5, 18, 20, 27, 41, 43, 56, 64, 68, 83, 92, 102, 109, 121, 123, 133, 143, 145, 155, 157, 170, 184, 193, 195, 203, 213, 216, 226, 244, 255, 257, 274, 284, 297, 309, 311, 324, 337, 339, 350, 363, 366, 376, 386, 395, 403, 406, 416, 418, 425, 435, 439, 448, 457, 469, 483, 497, 507, 509, 521, 529, 539, 548, 555, 559, 567, 576, 582, 584, 593, 598, 601, 605, 608, 613, 617, 629, 649, 651, 668, 681, 683, 698, 709, 716, 718, 728, 741, 753, 759, 768, 784, 798, 808, 822, 829, 837, 850, 858, 862, 877, 886, 896, 899, 905, 917, 926, 933, 935, 947, 956, 960, 973, 977, 979, 989, 999, 1001, 1010, 1017, 1020, 1030, 1032, 1045, 1047, 1053, 1055, 1066, 1077, 1084, 1094, 1104, 1119, 1121, 1131, 1145, 1154, 1166, 1169, 1180, 1186, 1194, 1203, 1215, 1228, 1240, 1254, 1258, 1273, 1281, 1291, 1298, 1300, 1309, 1319, 1326, 1328, 1340, 1351, 1353, 1371, 1383, 1387, 1395, 1407, 1409, 1419, 1429, 1431, 1441, 1443, 1456, 1470, 1480, 1484, 1486, 1495, 1503, 1514, 1520, 1531, 1539, 1542, 1550, 1557, 1564, 1573, 1575, 1587, 1596, 1606, 1608, 1620], "word_end_chars": [4, 17, 19, 26, 40, 42, 55, 63, 67, 82, 91, 101, 108, 120, 122, 132, 142, 144, 154, 156, 169, 183, 192, 194, 202, 212, 215, 225, 243, 254, 256, 273, 283, 296, 308, 310, 323, 336, 338, 349, 362, 365, 375, 385, 394, 402, 405, 415, 417, 424, 434, 438, 447, 456, 468, 482, 496, 505, 508, 520, 528, 538, 547, 554, 558, 566, 575, 581, 583, 592, 597, 600, 604, 607, 612, 616, 628, 648, 650, 667, 680, 682, 697, 708, 715, 717, 727, 740, 752, 758, 767, 783, 797, 807, 821, 828, 836, 849, 857, 861, 876, 885, 895, 898, 904, 916, 925, 932, 934, 946, 955, 959, 972, 976, 978, 988, 998, 1000, 1009, 1016, 1019, 1029, 1031, 1044, 1046, 1052, 1054, 1065, 1076, 1083, 1093, 1103, 1118, 1120, 1130, 1144, 1153, 1165, 1168, 1179, 1185, 1193, 1202, 1214, 1227, 1239, 1253, 1257, 1272, 1280, 1290, 1297, 1299, 1308, 1318, 1325, 1327, 1339, 1350, 1352, 1370, 1382, 1386, 1394, 1406, 1408, 1418, 1428, 1430, 1440, 1442, 1455, 1469, 1479, 1483, 1485, 1494, 1502, 1513, 1519, 1530, 1538, 1541, 1549, 1556, 1563, 1572, 1574, 1586, 1595, 1605, 1607, 1619, 1630]}